LICENSE.txt
README.md
dataclass_struct.py
setup.cfg
setup.py
dataclass_struct.egg-info/PKG-INFO
dataclass_struct.egg-info/SOURCES.txt
dataclass_struct.egg-info/dependency_links.txt
dataclass_struct.egg-info/top_level.txt