Metadata-Version: 2.1
Name: dataclass-struct
Version: 0.9.3
Summary: Decorator for writing and reading the dataclass as binary buffer using struct.
Home-page: https://https://github.com/Thinkeye/dataclass_struct
Author: Peter Krahulik
Author-email: peter.krahulik@googlemail.com
License: MIT
Keywords: dataclass,struct
Platform: UNKNOWN
Classifier: Programming Language :: Python :: 3
Classifier: License :: OSI Approved :: MIT License
Classifier: Operating System :: OS Independent
